{
  "@context": "http://iiif.io/api/presentation/3/context.json",
  "id": "https://Amcclu.github.io/mendoza-interview/annotations/mendoza-interview-canvas-1-interviewer--rapport--clarifying--specific-question.json",
  "type": "AnnotationPage",
  "label": "Interviewer: Rapport, Clarifying, Specific Question",
  "items": [
    {
      "@context": "http://www.w3.org/ns/anno.jsonld",
      "id": "mendoza-interview-canvas-1-interviewer--rapport--clarifying--specific-question-annotation-0.json",
      "type": "Annotation",
      "motivation": [
        "supplementing",
        "commenting"
      ],
      "body": {
        "type": "TextualBody",
        "value": "Actually, that now that you bring, bring that issue up about openness, and its relation to diversity, how were – were there any trends in how duties were assigned? Were there any differences?",
        "format": "text/plain",
        "purpose": "commenting"
      },
      "target": {
        "source": {
          "id": "https://Amcclu.github.io/mendoza-interview/mendoza-interview/canvas-1/canvas",
          "type": "Canvas",
          "partOf": [
            {
              "id": "https://Amcclu.github.io/mendoza-interview/mendoza-interview/manifest.json",
              "type": "Manifest"
            }
          ]
        },
        "selector": {
          "type": "PointSelector",
          "t": "34.0"
        }
      }
    }
  ]
}